webpages/__init__.py
webpages/controller.py
webpages/main.py
webpages/models.py
webpages/router.py
webpages/settings.py
webpages/tools.py
webpages/middleware/__init__.py
webpages/middleware/cookie.py
webpages/middleware/session.py
webpages/middleware/user.py
WebPages-1.0.0a2.dist-info/DESCRIPTION.rst
WebPages-1.0.0a2.dist-info/METADATA
WebPages-1.0.0a2.dist-info/metadata.json
WebPages-1.0.0a2.dist-info/RECORD
WebPages-1.0.0a2.dist-info/top_level.txt
WebPages-1.0.0a2.dist-info/WHEEL
