Metadata-Version: 2.0
Name: WebPages
Version: 1.0.0a2
Summary: WebPages - python web framework
Home-page: https://github.com/webpages/webpages
Author: Anton Danilchenko
Author-email: anton@danilchenko.me
License: MIT
Keywords: web framework development
Platform: any
Classifier: Development Status :: 3 - Alpha
Classifier: Environment :: Web Environment
Classifier: Intended Audience :: Developers
Classifier: License :: OSI Approved :: MIT License
Classifier: Operating System :: OS Independent
Classifier: Programming Language :: Python
Classifier: Programming Language :: Python :: 3
Classifier: Programming Language :: Python :: 3.3
Classifier: Programming Language :: Python :: 3.4
Classifier: Topic :: Internet :: WWW/HTTP :: Dynamic Content
Classifier: Topic :: Software Development :: Libraries :: Python Modules
Requires-Dist: webob
